git_user_manager/__init__.py
git_user_manager/__main__.py
git_user_manager-1.0.1.dist-info/LICENSE
git_user_manager-1.0.1.dist-info/METADATA
git_user_manager-1.0.1.dist-info/WHEEL
git_user_manager-1.0.1.dist-info/entry_points.txt
git_user_manager-1.0.1.dist-info/top_level.txt
git_user_manager-1.0.1.dist-info/RECORD
