Metadata-Version: 2.1
Name: git-user-manager
Version: 1.0.1
Summary: A tool to manage git user profile from the terminal
Author: Im Geek (Ankush Bhagat)
Author-email: <imegeek@gmail.com>
Keywords: user management,git,terminal
Classifier: Intended Audience :: Developers
Classifier: Programming Language :: Python :: 3
Classifier: Operating System :: Unix
Classifier: Operating System :: MacOS :: MacOS X
Classifier: Operating System :: Microsoft :: Windows
License-File: LICENSE
Requires-Dist: inquirerpy
